README.md
briticle.py
setup.py
briticle.egg-info/PKG-INFO
briticle.egg-info/SOURCES.txt
briticle.egg-info/dependency_links.txt
briticle.egg-info/top_level.txt